README.txt
setup.cfg
setup.py
django_arecibo/__init__.py
django_arecibo/arecibo.py
django_arecibo/log.py
django_arecibo/middleware.py
django_arecibo/tasks.py
django_arecibo/wrapper.py
django_arecibo.egg-info/PKG-INFO
django_arecibo.egg-info/SOURCES.txt
django_arecibo.egg-info/dependency_links.txt
django_arecibo.egg-info/entry_points.txt
django_arecibo.egg-info/not-zip-safe
django_arecibo.egg-info/requires.txt
django_arecibo.egg-info/top_level.txt
django_arecibo/tests/__init__.py
django_arecibo/tests/settings.py
django_arecibo/tests/test_wrapper.py