Metadata-Version: 1.0
Name: django-arecibo
Version: 0.3.4dev
Summary: Connector from Django to Arecibo
Home-page: http://clearwind.ca
Author: Clearwind Consulting
Author-email: andy@clearwind.ca
License: BSD
Platform: UNKNOWN
Classifier: Framework :: Django
Classifier: Programming Language :: Python
Classifier: Topic :: Software Development :: Libraries :: Python Modules
